xfarm/__init__.py
xfarm/__main__.py
xfarm-1.2.12.dist-info/METADATA
xfarm-1.2.12.dist-info/WHEEL
xfarm-1.2.12.dist-info/top_level.txt
xfarm-1.2.12.dist-info/RECORD
